alu.v
module alu(
    input [7:0] A, B,              // 8-bit Inputs
    input [3:0] ALU_Sel,           // 4-bit ALU operation selector
    output reg [15:0] ALU_Result,  // 16-bit Output to support multiplication
    output reg [7:0] Quotient,     // For division
    output reg [7:0] Remainder,    // For division
    output CarryOut,               // Carry Out Flag for addition
    output reg DivideByZero        // Optional error flag
);

    wire [8:0] tmp; // For carry out from 8-bit addition
    assign tmp = {1'b0, A} + {1'b0, B};
    assign CarryOut = tmp[8]; // 9th bit is the carry

    always @(*) begin
        // Default outputs
        Quotient = 8'd0;
        Remainder = 8'd0;
        DivideByZero = 1'b0; // Default: no error

        case (ALU_Sel)
            4'b0000: // Addition
                ALU_Result = A + B;

            4'b0001: // Subtraction
                ALU_Result = A - B;

            4'b0010: // Multiplication
                ALU_Result = A * B;

            4'b0011: begin // Division
                if (B != 0) begin
                    Quotient = A / B;
                    Remainder = A % B;
                    ALU_Result = {8'd0, Quotient}; // To display quotient in result
                end else begin
                    DivideByZero = 1'b1;
                    Quotient = 8'hFF;             // Error value
                    Remainder = 8'hFF;
                    ALU_Result = 16'hDEAD;        // Chosen error code for undefined
                end
            end

            4'b0100: // Logical shift left
                ALU_Result = A << 1;

            4'b0101: // Logical shift right
                ALU_Result = A >> 1;

            4'b0110: // Rotate left
                ALU_Result = {A[6:0], A[7]};

            4'b0111: // Rotate right
                ALU_Result = {A[0], A[7:1]};

            4'b1000: // AND
                ALU_Result = A & B;

            4'b1001: // OR
                ALU_Result = A | B;

            4'b1010: // XOR
                ALU_Result = A ^ B;

            4'b1011: // NOR
                ALU_Result = ~(A | B);

            4'b1100: // NAND
                ALU_Result = ~(A & B);

            4'b1101: // XNOR
                ALU_Result = ~(A ^ B);

            4'b1110: // Greater
                ALU_Result = (A > B) ? 16'd1 : 16'd0;

            4'b1111: // Equal
                ALU_Result = (A == B) ? 16'd1 : 16'd0;

            default:
                ALU_Result = 16'd0;
        endcase
    end

endmodule

alu_tb.v
`timescale 1ns / 1ps

module alu_tb;

    // Testbench variables
    reg [7:0] A, B;
    reg [3:0] ALU_Sel;
    wire [15:0] ALU_Result;
    wire [7:0] Quotient, Remainder;
    wire CarryOut;
    wire DivideByZero;

    // Instantiate the ALU
    alu uut (
        .A(A),
        .B(B),
        .ALU_Sel(ALU_Sel),
        .ALU_Result(ALU_Result),
        .Quotient(Quotient),
        .Remainder(Remainder),
        .CarryOut(CarryOut),
        .DivideByZero(DivideByZero)
    );

    // Task to display results nicely
    task display_output;
    begin
        $display("ALU_Sel=%b | A=%d, B=%d => Result=%d, Quotient=%d, Remainder=%d, CarryOut=%b, DivideByZero=%b", 
                 ALU_Sel, A, B, ALU_Result, Quotient, Remainder, CarryOut, DivideByZero);
    end
    endtask

    initial begin
        // Dump waves for GTKWave
        $dumpfile("alu_tb.vcd");       // VCD file name
        $dumpvars(0, alu_tb);          // Dump all variables in this module and below

        // Test Addition
        A = 8'd20; B = 8'd15; ALU_Sel = 4'b0000; #10; display_output();

        // Test Subtraction
        A = 8'd30; B = 8'd10; ALU_Sel = 4'b0001; #10; display_output();

        // Test Multiplication
        A = 8'd7; B = 8'd6; ALU_Sel = 4'b0010; #10; display_output();

        // Test Division - Normal
        A = 8'd40; B = 8'd5; ALU_Sel = 4'b0011; #10; display_output();

        // Test Division by Zero
        A = 8'd40; B = 8'd0; ALU_Sel = 4'b0011; #10; display_output();

        // Logical Shift Left
        A = 8'b00001111; B = 8'd0; ALU_Sel = 4'b0100; #10; display_output();

        // Logical Shift Right
        A = 8'b00001111; B = 8'd0; ALU_Sel = 4'b0101; #10; display_output();

        // AND Operation
        A = 8'b10101010; B = 8'b11001100; ALU_Sel = 4'b1000; #10; display_output();

        // OR Operation
        // Keep A and B same as previous since you didn't assign new values
        ALU_Sel = 4'b1001; #10; display_output();

        // XOR Operation
        ALU_Sel = 4'b1010; #10; display_output();

        // Equal
        A = 8'd25; B = 8'd25; ALU_Sel = 4'b1111; #10; display_output();

        // Greater
        A = 8'd50; B = 8'd20; ALU_Sel = 4'b1110; #10; display_output();

        $finish;
    end

endmodule

alu_tb.vcd
$date
	Mon Jun 09 09:14:29 2025
$end
$version
	Icarus Verilog
$end
$timescale
	1ps
$end
$scope module alu_tb $end
$var wire 8 ! Remainder [7:0] $end
$var wire 8 " Quotient [7:0] $end
$var wire 1 # DivideByZero $end
$var wire 1 $ CarryOut $end
$var wire 16 % ALU_Result [15:0] $end
$var reg 8 & A [7:0] $end
$var reg 4 ' ALU_Sel [3:0] $end
$var reg 8 ( B [7:0] $end
$scope module uut $end
$var wire 8 ) A [7:0] $end
$var wire 4 * ALU_Sel [3:0] $end
$var wire 8 + B [7:0] $end
$var wire 9 , tmp [8:0] $end
$var wire 1 $ CarryOut $end
$var reg 16 - ALU_Result [15:0] $end
$var reg 1 # DivideByZero $end
$var reg 8 . Quotient [7:0] $end
$var reg 8 / Remainder [7:0] $end
$upscope $end
$scope task display_output $end
$upscope $end
$upscope $end
$enddefinitions $end
$comment Show the parameter values. $end
$dumpall
$end
#0
$dumpvars
b0 /
b0 .
b100011 -
b100011 ,
b1111 +
b0 *
b10100 )
b1111 (
b0 '
b10100 &
b100011 %
0$
0#
b0 "
b0 !
$end
#10000
b10100 %
b10100 -
b1 '
b1 *
b1010 (
b1010 +
b101000 ,
b11110 &
b11110 )
#20000
b101010 %
b101010 -
b10 '
b10 *
b110 (
b110 +
b1101 ,
b111 &
b111 )
#30000
b1000 %
b1000 -
b1000 "
b1000 .
b11 '
b11 *
b101 (
b101 +
b101101 ,
b101000 &
b101000 )
#40000
b1101111010101101 %
b1101111010101101 -
b11111111 !
b11111111 /
1#
b11111111 "
b11111111 .
b101000 ,
b0 (
b0 +
#50000
b11110 %
b11110 -
0#
b0 !
b0 /
b0 "
b0 .
b100 '
b100 *
b1111 ,
b1111 &
b1111 )
#60000
b111 %
b111 -
b101 '
b101 *
#70000
1$
b10001000 %
b10001000 -
b1000 '
b1000 *
b11001100 (
b11001100 +
b101110110 ,
b10101010 &
b10101010 )
#80000
b11101110 %
b11101110 -
b1001 '
b1001 *
#90000
b1100110 %
b1100110 -
b1010 '
b1010 *
#100000
b1 %
b1 -
0$
b1111 '
b1111 *
b11001 (
b11001 +
b110010 ,
b11001 &
b11001 )
#110000
b1110 '
b1110 *
b10100 (
b10100 +
b1000110 ,
b110010 &
b110010 )
