full_adder.v
module full_adder (
    input a,       // First input bit
    input b,       // Second input bit
    input cin,     // Carry input
    output sum,    // Sum output
    output cout    // Carry output
);

assign sum = a ^ b ^ cin;          // Sum is XOR of inputs and carry in
assign cout = (a & b) | (b & cin) | (a & cin);  // Carry out is majority function

endmodule

full_adder_tb.v
`timescale 1ns/1ps

module full_adder_tb;

reg a, b, cin;
wire sum, cout;

// Instantiate the full_adder module
full_adder uut (
    .a(a),
    .b(b),
    .cin(cin),
    .sum(sum),
    .cout(cout)
);

initial begin
    // VCD dump for GTKWave
    $dumpfile("full_adder_tb.vcd");
    $dumpvars(0, full_adder_tb);

    // Initialize inputs and display header
    $display("a b cin | sum cout");
    $display("-------------------");

    // Test all possible input combinations (0 to 7)
    a = 0; b = 0; cin = 0; #10;
    $display("%b %b  %b  |  %b   %b", a, b, cin, sum, cout);

    a = 0; b = 0; cin = 1; #10;
    $display("%b %b  %b  |  %b   %b", a, b, cin, sum, cout);

    a = 0; b = 1; cin = 0; #10;
    $display("%b %b  %b  |  %b   %b", a, b, cin, sum, cout);

    a = 0; b = 1; cin = 1; #10;
    $display("%b %b  %b  |  %b   %b", a, b, cin, sum, cout);

    a = 1; b = 0; cin = 0; #10;
    $display("%b %b  %b  |  %b   %b", a, b, cin, sum, cout);

    a = 1; b = 0; cin = 1; #10;
    $display("%b %b  %b  |  %b   %b", a, b, cin, sum, cout);

    a = 1; b = 1; cin = 0; #10;
    $display("%b %b  %b  |  %b   %b", a, b, cin, sum, cout);

    a = 1; b = 1; cin = 1; #10;
    $display("%b %b  %b  |  %b   %b", a, b, cin, sum, cout);

    $finish;
end

endmodule

full_adder_tb.vcd
$date
	Sat May 31 16:29:28 2025
$end
$version
	Icarus Verilog
$end
$timescale
	1ps
$end
$scope module full_adder_tb $end
$var wire 1 ! sum $end
$var wire 1 " cout $end
$var reg 1 # a $end
$var reg 1 $ b $end
$var reg 1 % cin $end
$scope module uut $end
$var wire 1 # a $end
$var wire 1 $ b $end
$var wire 1 % cin $end
$var wire 1 " cout $end
$var wire 1 ! sum $end
$upscope $end
$upscope $end
$enddefinitions $end
$comment Show the parameter values. $end
$dumpall
$end
#0
$dumpvars
0%
0$
0#
0"
0!
$end
#10000
1!
1%
#20000
0%
1$
#30000
1"
0!
1%
#40000
0"
1!
0%
0$
1#
#50000
1"
0!
1%
#60000
0%
1$
#70000
1!
1%
